mqtthandler
