Metadata-Version: 2.1
Name: mqtthandler
Version: 0.1.5
Summary: A Python logging handler using MQTT protocol
Home-page: https://github.com/changyuheng/MQTTHandler.py
Author: Johann Chang
Author-email: mr.changyuheng@gmail.com
License: MPL-2.0
Platform: UNKNOWN
License-File: LICENSE
